{	
"items": {	
"data" : [	
{	
"id" :	 "1", 
"nombre":	 "BANCOLOMBIA", 
 "per" : 	" 6,79",
 "pvl" : 	" 1,00",
"roe" :	" 15%",
"yield" :	" 8,28%",
"ytd" :	" 13,56%"
},	
{	
"id" :	 "2", 
"nombre":	 "BANCOLOMBIA PF", 
 "per" : 	" 6,47",
 "pvl" : 	" 0,96",
"roe" :	" 15%",
"yield" :	" 8,69%",
"ytd" :	" 15,69%"
},	
{	
"id" :	 "3", 
"nombre":	 "BANCO DE BOGOTA", 
 "per" : 	" 12,70",
 "pvl" : 	" 0,63",
"roe" :	" 5,0%",
"yield" :	" 4,96%",
"ytd" :	" 9,08%"
},	
{	
"id" :	 "4", 
"nombre":	 "BHI", 
 "per" : 	" 4,69",
 "pvl" : 	" 0,70",
"roe" :	" 14,8%",
"yield" :	" 8,34%",
"ytd" :	" 0,67%"
},	
{	
"id" :	 "5", 
"nombre":	 "CELSIA", 
 "per" : 	" 18,93",
 "pvl" : 	" 1,09",
"roe" :	" 5,7%",
"yield" :	" 8,42%",
"ytd" :	" 0,00%"
},	
{	
"id" :	 "6", 
"nombre":	 "CEMENTOS ARGOS", 
 "per" : 	" 2,67",
 "pvl" : 	" 1,18",
"roe" :	" 44,1%",
"yield" :	" 3,33%",
"ytd" :	" 3,14%"
},	
{	
"id" :	 "7", 
"nombre":	 "CONCONCRETO", 
 "per" : 	" 37,25",
 "pvl" : 	" 0,51",
"roe" :	" 1,4%",
"yield" :	" 0,00%",
"ytd" :	" 33,74%"
},	
{	
"id" :	 "8", 
"nombre":	 "CORFICOLOMBIANA", 
 "per" : 	" 20,55",
 "pvl" : 	" 0,51",
"roe" :	" 2,5%",
"yield" :	" 0,00%",
"ytd" :	" 19,35%"
},	
{	
"id" :	 "9", 
"nombre":	 "CORFICOLOMBIANA PF", 
 "per" : 	" 18,41",
 "pvl" : 	" 0,46",
"roe" :	" 2,5%",
"yield" :	" 0,00%",
"ytd" :	" 38,94%"
},	
{	
"id" :	 "10", 
"nombre":	 "DAVIVIENDA PF", 
 "per" : 	" -17,34",
 "pvl" : 	" 0,60",
"roe" :	" -3,5%",
"yield" :	" 0,00%",
"ytd" :	" 8,66%"
},	
{	
"id" :	 "11", 
"nombre":	 "ECOPETROL", 
 "per" : 	" 5,35",
 "pvl" : 	" 1,04",
"roe" :	" 19,5%",
"yield" :	" 15,72%",
"ytd" :	" 18,51%"
},	
{	
"id" :	 "12", 
"nombre":	 "EXITO", 
 "per" : 	" 88,05",
 "pvl" : 	" 0,31",
"roe" :	" 0,4%",
"yield" :	" 2,71%",
"ytd" :	" -11,22%"
},	
{	
"id" :	 "13", 
"nombre":	 "GEB", 
 "per" : 	" 9,84",
 "pvl" : 	" 1,27",
"roe" :	" 12,9%",
"yield" :	" 9,62%",
"ytd" :	" 6,97%"
},	
{	
"id" :	 "14", 
"nombre":	 "ENKA", 
 "per" : 	" 14,01",
 "pvl" : 	" 0,36",
"roe" :	" 2,6%",
"yield" :	" 7,84%",
"ytd" :	" 18,60%"
},	
{	
"id" :	 "15", 
"nombre":	 "GRUPO ARGOS", 
 "per" : 	" 3,93",
 "pvl" : 	" 0,77",
"roe" :	" 19,6%",
"yield" :	" 3,21%",
"ytd" :	" -3,79%"
},	
{	
"id" :	 "16", 
"nombre":	 "GRUPO ARGOS PF", 
 "per" : 	" 2,92",
 "pvl" : 	" 0,57",
"roe" :	" 19,6%",
"yield" :	" 4,32%",
"ytd" :	" -4,66%"
},	
{	
"id" :	 "17", 
"nombre":	 "GRUPO AVAL PF", 
 "per" : 	" 15,17",
 "pvl" : 	" 0,71",
"roe" :	" 4,7%",
"yield" :	" 4,32%",
"ytd" :	" 24,66%"
},	
{	
"id" :	 "18", 
"nombre":	 "GRUPO BOLIVAR", 
 "per" : 	" 9,65",
 "pvl" : 	" 0,34",
"roe" :	" 3,5%",
"yield" :	" 10,36%",
"ytd" :	" 2,32%"
},	
{	
"id" :	 "19", 
"nombre":	 "GRUPO SURA", 
 "per" : 	" 2,52",
 "pvl" : 	" 0,56",
"roe" :	" 22,1%",
"yield" :	" 3,81%",
"ytd" :	" -1,34%"
},	
{	
"id" :	 "20", 
"nombre":	 "GRUPO SURA PF", 
 "per" : 	" 2,02",
 "pvl" : 	" 0,45",
"roe" :	" 22,1%",
"yield" :	" 4,74%",
"ytd" :	" 13,53%"
},	
{	
"id" :	 "21", 
"nombre":	 "ISA", 
 "per" : 	" 7,48",
 "pvl" : 	" 1,14",
"roe" :	" 15%",
"yield" :	" 6,17%",
"ytd" :	" 7,78%"
},	
{	
"id" :	 "22", 
"nombre":	 "MINEROS", 
 "per" : 	" 4,23",
 "pvl" : 	" 0,93",
"roe" :	" 21,9%",
"yield" :	" 7,44%",
"ytd" :	" 14,57%"
},	
{	
"id" :	 "23", 
"nombre":	 "PEI", 
 "per" : 	" 3,65",
 "pvl" : 	" 0,53",
"roe" :	" 14%",
"yield" :	" 0,00%",
"ytd" :	" 0,57%"
},	
{	
"id" :	 "24", 
"nombre":	 "PROMIGAS", 
 "per" : 	" 7,09",
 "pvl" : 	" 1,27",
"roe" :	" 18,0%",
"yield" :	" 7,46%",
"ytd" :	" -3,89%"
},	
{	
"id" :	 "25", 
"nombre":	 "TERPEL", 
 "per" : 	" 4,52",
 "pvl" : 	" 0,70",
"roe" :	" 16%",
"yield" :	" 6,40%",
"ytd" :	" 6,78%"
}]}}	

